{"__type__":"cc.JsonAsset","_name":"DaoGuanZhan_GeRenPaiMing","json":{"1001":{"RankBegin":1,"RankEnd":1,"PoolID":1101},"1002":{"RankBegin":2,"RankEnd":2,"PoolID":1102},"1003":{"RankBegin":3,"RankEnd":3,"PoolID":1103},"1004":{"RankBegin":4,"RankEnd":5,"PoolID":1104},"1005":{"RankBegin":6,"RankEnd":10,"PoolID":1105},"1006":{"RankBegin":11,"RankEnd":50,"PoolID":1106},"1007":{"RankBegin":51,"RankEnd":200,"PoolID":1107},"1008":{"RankBegin":201,"RankEnd":500,"PoolID":1108},"1009":{"RankBegin":501,"RankEnd":1000,"PoolID":1109},"2001":{"RankBegin":1,"RankEnd":1,"PoolID":1101},"2002":{"RankBegin":2,"RankEnd":2,"PoolID":1102},"2003":{"RankBegin":3,"RankEnd":3,"PoolID":1103},"2004":{"RankBegin":4,"RankEnd":5,"PoolID":1104},"2005":{"RankBegin":6,"RankEnd":10,"PoolID":1105},"2006":{"RankBegin":11,"RankEnd":50,"PoolID":1106},"2007":{"RankBegin":51,"RankEnd":200,"PoolID":1107},"2008":{"RankBegin":201,"RankEnd":500,"PoolID":1108},"2009":{"RankBegin":501,"RankEnd":1000,"PoolID":1109},"3001":{"RankBegin":1,"RankEnd":1,"PoolID":1101},"3002":{"RankBegin":2,"RankEnd":2,"PoolID":1102},"3003":{"RankBegin":3,"RankEnd":3,"PoolID":1103},"3004":{"RankBegin":4,"RankEnd":5,"PoolID":1104},"3005":{"RankBegin":6,"RankEnd":10,"PoolID":1105},"3006":{"RankBegin":11,"RankEnd":50,"PoolID":1106},"3007":{"RankBegin":51,"RankEnd":200,"PoolID":1107},"3008":{"RankBegin":201,"RankEnd":500,"PoolID":1108},"3009":{"RankBegin":501,"RankEnd":1000,"PoolID":1109},"4001":{"RankBegin":1,"RankEnd":1,"PoolID":1101},"4002":{"RankBegin":2,"RankEnd":2,"PoolID":1102},"4003":{"RankBegin":3,"RankEnd":3,"PoolID":1103},"4004":{"RankBegin":4,"RankEnd":5,"PoolID":1104},"4005":{"RankBegin":6,"RankEnd":10,"PoolID":1105},"4006":{"RankBegin":11,"RankEnd":50,"PoolID":1106},"4007":{"RankBegin":51,"RankEnd":200,"PoolID":1107},"4008":{"RankBegin":201,"RankEnd":500,"PoolID":1108},"4009":{"RankBegin":501,"RankEnd":1000,"PoolID":1109}}}