{"__type__":"cc.JsonAsset","_name":"BaiWan_JinHuaYueShi","json":{"101201":{"Name":"小山猪进化钥石","Icon":"HF-XiaoShanZhu","Define":"解锁小山猪百万进化的神奇钥石，将钥石品质跃升到红色品质，小山猪进化+6后精灵进化接口即可解锁超酷的百万进化。","PieceID":705,"CardID":1012010,"Des":["工作最终金币+【x】","冰属性精灵：初始生命+【x】\\n冰属性精灵：初始物防+【x1】","冰属性精灵：初始生命+【x】\\n冰属性精灵：初始法防+【x1】","冰属性精灵：初始生命+【x】\\n冰属性精灵：初始攻击+【x1】"],"ProOneID":[2009,52,52,52],"ValueOne":[10000,50,50,50],"TargetOne":[516,517,517,517],"AddOne":[10000,50,50,50],"MulOne":[10000,10000,10000,10000],"ProTwoID":[53,54,51],"ValuTwo":[50,50,50],"TargetTwo":[517,517,517],"AddTwo":[50,50,50],"MulTwo":[10000,10000,10000],"FinalTitle":["百万进化","生命蜕变","种族跃迁"],"FinalDas":["小山猪进化+6后解锁百万进化，百万进化效果：品质提升为红色，实力大幅提升，技能效果大幅提升！","冰属性精灵：初始生命+25%\\n队伍精灵：强化等级上限+40","小山猪所有进化形态，初始攻击+20，初始生命+200，初始防御+4\\n小山猪+1，强化等级上限额外+5\\n小山猪+2，强化等级上限额外+10\\n小山猪+3，强化等级上限额外+15\\n小山猪+4，强化等级上限额外+20\\n小山猪+5，强化等级上限额外+25\\n小山猪+6，强化等级上限额外+30\\n超级小山猪，强化等级上限额外+35"],"RedID":[1,2,30,3210,52,0],"RedValue":[20,200,4,40,2500,0],"RedTarget":[540,540,540,516,517,0],"LevelBonus":[5,10,15,20,25,30,35]},"101501":{"Name":"急冻鸟进化钥石","Icon":"HF-JiDongNiao","Define":"解锁急冻鸟百万进化的神奇钥石，将钥石品质跃升到红色品质，急冻鸟进化+6后精灵进化接口即可解锁超酷的百万进化。","PieceID":762,"CardID":1015010,"Des":["工作最终金币+【x】","精灵强化金币-【x】","工作升级金币-【x】","冰属性精灵：初始暴率+【x】\\n冰属性精灵：初始暴伤+【x1】"],"ProOneID":[2009,2007,2006,8],"ValueOne":[30000,12000,12000,50],"TargetOne":[516,516,516,517],"AddOne":[10000,0,0,50],"MulOne":[10000,12078,12078,10000],"ProTwoID":9,"ValuTwo":50,"TargetTwo":517,"AddTwo":50,"MulTwo":10000,"FinalTitle":["百万进化","狂暴光环","种族跃迁"],"FinalDas":["急冻鸟进化+6后解锁百万进化，百万进化效果：实力大幅提升，技能效果大幅提升！","冰属性精灵：初始暴率+5%\\n冰属性精灵：初始暴伤+25%\\n队伍精灵：强化等级上限+40","急冻鸟所有进化形态，初始攻击+20，初始生命+200，初始防御+4\\n急冻鸟+1，强化等级上限额外+20\\n急冻鸟+2，强化等级上限额外+40\\n急冻鸟+3，强化等级上限额外+60\\n急冻鸟+4，强化等级上限额外+80\\n急冻鸟+5，强化等级上限额外+100\\n急冻鸟+6，强化等级上限额外+120\\n超级急冻鸟，强化等级上限额外+140"],"RedID":[1,2,30,3210,8,9],"RedValue":[20,200,4,40,500,500],"RedTarget":[540,540,540,516,517,517],"LevelBonus":[20,40,60,80,100,120,140]},"102401":{"Name":"圆陆鲨进化钥石","Icon":"HF-YuanLuSha","Define":"解锁圆陆鲨百万进化的神奇钥石，将钥石品质跃升到红色品质，圆陆鲨进化+6后精灵进化接口即可解锁超酷的百万进化。","PieceID":725,"CardID":1024010,"Des":["工作最终金币+【x】","龙属性精灵：初始生命+【x】\\n龙属性精灵：初始物防+【x1】","龙属性精灵：初始生命+【x】\\n龙属性精灵：初始法防+【x1】","龙属性精灵：初始生命+【x】\\n龙属性精灵：初始攻击+【x1】"],"ProOneID":[2009,52,52,52],"ValueOne":[10000,50,50,50],"TargetOne":[516,518,518,518],"AddOne":[10000,50,50,50],"MulOne":[10000,10000,10000,10000],"ProTwoID":[53,54,51],"ValuTwo":[50,50,50],"TargetTwo":[518,518,518],"AddTwo":[50,50,50],"MulTwo":[10000,10000,10000],"FinalTitle":["百万进化","生命蜕变","种族跃迁"],"FinalDas":["圆陆鲨进化+6后解锁百万进化，百万进化效果：品质提升为红色，实力大幅提升，技能效果大幅提升！","龙属性精灵：初始生命+25%\\n队伍精灵：强化等级上限+40","圆陆鲨所有进化形态，初始攻击+20，初始生命+200，初始防御+4\\n圆陆鲨+1，强化等级上限额外+10\\n圆陆鲨+2，强化等级上限额外+20\\n圆陆鲨+3，强化等级上限额外+30\\n圆陆鲨+4，强化等级上限额外+40\\n圆陆鲨+5，强化等级上限额外+50\\n圆陆鲨+6，强化等级上限额外+60\\n超级圆陆鲨，强化等级上限额外+70"],"RedID":[1,2,30,3210,52,0],"RedValue":[20,200,4,40,2500,0],"RedTarget":[540,540,540,516,518,0],"LevelBonus":[10,20,30,40,50,60,70]},"102501":{"Name":"烈空坐进化钥石","Icon":"HF-LieKongZuo","Define":"解锁烈空坐百万进化的神奇钥石，将钥石品质跃升到红色品质，烈空坐进化+6后精灵进化接口即可解锁超酷的百万进化。","PieceID":763,"CardID":1025010,"Des":["工作最终金币+【x】","精灵强化金币-【x】","工作升级金币-【x】","龙属性精灵：初始暴率+【x】\\n龙属性精灵：初始暴伤+【x1】"],"ProOneID":[2009,2007,2006,8],"ValueOne":[30000,12000,12000,50],"TargetOne":[516,516,516,518],"AddOne":[10000,0,0,50],"MulOne":[10000,12078,12078,10000],"ProTwoID":9,"ValuTwo":50,"TargetTwo":518,"AddTwo":50,"MulTwo":10000,"FinalTitle":["百万进化","狂暴光环","种族跃迁"],"FinalDas":["烈空坐进化+6后解锁百万进化，百万进化效果：实力大幅提升，技能效果大幅提升！","龙属性精灵：初始暴率+5%\\n龙属性精灵：初始暴伤+25%\\n队伍精灵：强化等级上限+40","烈空坐所有进化形态，初始攻击+20，初始生命+200，初始防御+4\\n烈空坐+1，强化等级上限额外+20\\n烈空坐+2，强化等级上限额外+40\\n烈空坐+3，强化等级上限额外+60\\n烈空坐+4，强化等级上限额外+80\\n烈空坐+5，强化等级上限额外+100\\n烈空坐+6，强化等级上限额外+120\\n超级烈空坐，强化等级上限额外+140"],"RedID":[1,2,30,3210,8,9],"RedValue":[20,200,4,40,500,500],"RedTarget":[540,540,540,516,518,518],"LevelBonus":[20,40,60,80,100,120,140]},"102502":{"Name":"拉帝亚斯进化钥石","Icon":"HF-LaDiYaSi","Define":"解锁拉帝亚斯百万进化的神奇钥石，将钥石品质跃升到红色品质，拉帝亚斯进化+6后精灵进化接口即可解锁超酷的百万进化。","PieceID":764,"CardID":1025020,"Des":["工作最终金币+【x】","精灵强化金币-【x】","工作升级金币-【x】","工作时间-【x】"],"ProOneID":[2009,2007,2006,2003],"ValueOne":[30000,15000,15000,15000],"TargetOne":[516,516,516,516],"AddOne":[10000,0,0,0],"MulOne":[10000,12195,12195,11845],"ProTwoID":0,"ValuTwo":0,"TargetTwo":0,"AddTwo":0,"MulTwo":0,"FinalTitle":["百万进化","大师纹章","种族跃迁"],"FinalDas":["拉帝亚斯进化+6后解锁百万进化，百万进化效果：实力大幅提升，技能效果大幅提升！","开启礼盒：礼盒纹章+1500%\\n队伍精灵：强化等级上限+40","拉帝亚斯所有进化形态，初始攻击+20，初始生命+200，初始防御+4\\n拉帝亚斯+1，强化等级上限额外+20\\n拉帝亚斯+2，强化等级上限额外+40\\n拉帝亚斯+3，强化等级上限额外+60\\n拉帝亚斯+4，强化等级上限额外+80\\n拉帝亚斯+5，强化等级上限额外+100\\n拉帝亚斯+6，强化等级上限额外+120\\n超级拉帝亚斯，强化等级上限额外+140"],"RedID":[1,2,30,3210,3709,0],"RedValue":[20,200,4,40,150000,0],"RedTarget":[540,540,540,516,516,0],"LevelBonus":[20,40,60,80,100,120,140]},"102503":{"Name":"拉帝欧斯进化钥石","Icon":"HF-LaDiOuSi","Define":"解锁拉帝欧斯百万进化的神奇钥石，将钥石品质跃升到红色品质，拉帝欧斯进化+6后精灵进化接口即可解锁超酷的百万进化。","PieceID":765,"CardID":1025030,"Des":["工作最终金币+【x】","精灵强化金币-【x】","工作升级金币-【x】","工作时间-【x】"],"ProOneID":[2009,2007,2006,2003],"ValueOne":[30000,15000,15000,15000],"TargetOne":[516,516,516,516],"AddOne":[10000,0,0,0],"MulOne":[10000,12195,12195,11845],"ProTwoID":0,"ValuTwo":0,"TargetTwo":0,"AddTwo":0,"MulTwo":0,"FinalTitle":["百万进化","大师纹章","种族跃迁"],"FinalDas":["拉帝欧斯进化+6后解锁百万进化，百万进化效果：实力大幅提升，技能效果大幅提升！","通关关卡：掉落纹章+1000%\\n队伍精灵：强化等级上限+40","拉帝欧斯所有进化形态，初始攻击+20，初始生命+200，初始防御+4\\n拉帝欧斯+1，强化等级上限额外+20\\n拉帝欧斯+2，强化等级上限额外+40\\n拉帝欧斯+3，强化等级上限额外+60\\n拉帝欧斯+4，强化等级上限额外+80\\n拉帝欧斯+5，强化等级上限额外+100\\n拉帝欧斯+6，强化等级上限额外+120\\n超级拉帝欧斯，强化等级上限额外+140"],"RedID":[1,2,30,3210,3607,0],"RedValue":[20,200,4,40,100000,0],"RedTarget":[540,540,540,516,516,0],"LevelBonus":[20,40,60,80,100,120,140]},"103503":{"Name":"小火龙进化钥石","Icon":"HF-XiaoHuoLong","Define":"解锁小火龙百万进化的神奇钥石，将钥石品质跃升到红色品质，小火龙进化+6后精灵进化接口即可解锁超酷的百万进化。","PieceID":752,"CardID":1035030,"Des":["工作最终金币+【x】","火属性精灵：初始生命+【x】\\n火属性精灵：初始物防+【x1】","火属性精灵：初始生命+【x】\\n火属性精灵：初始法防+【x1】","火属性精灵：初始生命+【x】\\n火属性精灵：初始攻击+【x1】"],"ProOneID":[2009,52,52,52],"ValueOne":[10000,50,50,50],"TargetOne":[516,519,519,519],"AddOne":[10000,50,50,50],"MulOne":[10000,10000,10000,10000],"ProTwoID":[53,54,51],"ValuTwo":[50,50,50],"TargetTwo":[519,519,519],"AddTwo":[50,50,50],"MulTwo":[10000,10000,10000],"FinalTitle":["百万进化","生命蜕变","种族跃迁"],"FinalDas":["小火龙进化+6后解锁百万进化，百万进化效果：品质提升为红色，实力大幅提升，技能效果大幅提升！","火属性精灵：初始生命+25%\\n队伍精灵：强化等级上限+40","小火龙所有进化形态，初始攻击+20，初始生命+200，初始防御+4\\n火恐龙+1，强化等级上限额外+20\\n喷火龙+2，强化等级上限额外+40\\n喷火龙+3，强化等级上限额外+60\\n喷火龙+4，强化等级上限额外+80\\n喷火龙+5，强化等级上限额外+100\\n喷火龙+6，强化等级上限额外+120\\n超级喷火龙，强化等级上限额外+140"],"RedID":[1,2,30,3210,52,0],"RedValue":[20,200,4,40,2500,0],"RedTarget":[540,540,540,516,519,0],"LevelBonus":[15,30,45,60,75,90,105]},"103506":{"Name":"喷火驼进化钥石","Icon":"HF-PenHuoTuo","Define":"解锁喷火驼百万进化的神奇钥石，将钥石品质跃升到红色品质，喷火驼进化+6后精灵进化接口即可解锁超酷的百万进化。","PieceID":738,"CardID":1035060,"Des":["工作最终金币+【x】","里程碑纹章+【x】","里程碑纹章+【x】","火属性精灵：初始暴率+【x】\\n火属性精灵：初始暴伤+【x1】"],"ProOneID":[2009,3506,3506,8],"ValueOne":[10000,1000,1000,50],"TargetOne":[516,516,516,519],"AddOne":[10000,1000,1000,50],"MulOne":[10000,10000,10000,10000],"ProTwoID":9,"ValuTwo":50,"TargetTwo":519,"AddTwo":50,"MulTwo":10000,"FinalTitle":["百万进化","狂暴光环","种族跃迁"],"FinalDas":["喷火驼进化+6后解锁百万进化，百万进化效果：品质提升为红色，实力大幅提升，技能效果大幅提升！","火属性精灵：初始暴率+5%\\n火属性精灵：初始暴伤+25%\\n队伍精灵：强化等级上限+40","喷火驼所有进化形态，初始攻击+20，初始生命+200，初始防御+4\\n喷火驼+1，强化等级上限额外+20\\n喷火驼+2，强化等级上限额外+40\\n喷火驼+3，强化等级上限额外+60\\n喷火驼+4，强化等级上限额外+80\\n喷火驼+5，强化等级上限额外+100\\n喷火驼+6，强化等级上限额外+120\\n超级喷火驼，强化等级上限额外+140"],"RedID":[1,2,30,3210,8,9],"RedValue":[20,200,4,40,500,500],"RedTarget":[540,540,540,516,519,519],"LevelBonus":[15,30,45,60,75,90,105]},"104501":{"Name":"妙蛙种子进化钥石","Icon":"HF-MiaoWaZhongZi","Define":"解锁妙蛙种子百万进化的神奇钥石，将钥石品质跃升到红色品质，妙蛙种子进化+6后精灵进化接口即可解锁超酷的百万进化。","PieceID":753,"CardID":1045010,"Des":["工作时间-【x】","草属性精灵：初始生命+【x】\\n草属性精灵：初始物防+【x1】","草属性精灵：初始生命+【x】\\n草属性精灵：初始法防+【x1】","草属性精灵：初始生命+【x】\\n草属性精灵：初始攻击+【x1】"],"ProOneID":[2003,52,52,52],"ValueOne":[12000,50,50,50],"TargetOne":[516,520,520,520],"AddOne":[50,50,50],"MulOne":[11732,10000,10000,10000],"ProTwoID":[53,54,51],"ValuTwo":[50,50,50],"TargetTwo":[520,520,520],"AddTwo":[50,50,50],"MulTwo":[10000,10000,10000],"FinalTitle":["百万进化","生命蜕变","种族跃迁"],"FinalDas":["妙蛙种子进化+6后解锁百万进化，百万进化效果：品质提升为红色，实力大幅提升，技能效果大幅提升！","草属性精灵：初始生命+25%\\n队伍精灵：强化等级上限+40","妙蛙种子所有进化形态，初始攻击+20，初始生命+200，初始防御+4\\n妙蛙草+1，强化等级上限额外+20\\n妙蛙花+2，强化等级上限额外+40\\n妙蛙花+3，强化等级上限额外+60\\n妙蛙花+4，强化等级上限额外+80\\n妙蛙花+5，强化等级上限额外+100\\n妙蛙花+6，强化等级上限额外+120\\n超级妙蛙花，强化等级上限额外+140"],"RedID":[1,2,30,3210,52,0],"RedValue":[20,200,4,40,2500,0],"RedTarget":[540,540,540,516,520,0],"LevelBonus":[15,30,45,60,75,90,105]},"104503":{"Name":"木守宫进化钥石","Icon":"HF-MuShouGong","Define":"解锁木守宫百万进化的神奇钥石，将钥石品质跃升到红色品质，木守宫进化+6后精灵进化接口即可解锁超酷的百万进化。","PieceID":740,"CardID":1045030,"Des":["工作最终金币+【x】","里程碑纹章+【x】","里程碑纹章+【x】","草属性精灵：初始暴率+【x】\\n草属性精灵：初始暴伤+【x1】"],"ProOneID":[2009,3506,3506,8],"ValueOne":[10000,1000,1000,50],"TargetOne":[516,516,516,520],"AddOne":[10000,1000,1000,50],"MulOne":[10000,10000,10000,10000],"ProTwoID":9,"ValuTwo":50,"TargetTwo":520,"AddTwo":50,"MulTwo":10000,"FinalTitle":["百万进化","狂暴光环","种族跃迁"],"FinalDas":["木守宫进化+6后解锁百万进化，百万进化效果：品质提升为红色，实力大幅提升，技能效果大幅提升！","草属性精灵：初始暴率+5%\\n草属性精灵：初始暴伤+25%\\n队伍精灵：强化等级上限+40","木守宫所有进化形态，初始攻击+20，初始生命+200，初始防御+4\\n森林蜥蜴+1，强化等级上限额外+20\\n蜥蜴王+2，强化等级上限额外+40\\n蜥蜴王+3，强化等级上限额外+60\\n蜥蜴王+4，强化等级上限额外+80\\n蜥蜴王+5，强化等级上限额外+100\\n蜥蜴王+6，强化等级上限额外+120\\n超级蜥蜴王，强化等级上限额外+140"],"RedID":[1,2,30,3210,8,9],"RedValue":[20,200,4,40,500,500],"RedTarget":[540,540,540,516,520,520],"LevelBonus":[15,30,45,60,75,90,105]},"105301":{"Name":"暴鲤龙进化钥石","Icon":"HF-BaoLiLong","Define":"解锁暴鲤龙百万进化的神奇钥石，将钥石品质跃升到红色品质，暴鲤龙进化+6后精灵进化接口即可解锁超酷的百万进化。","PieceID":717,"CardID":1053010,"Des":["工作最终金币+【x】","里程碑纹章+【x】","里程碑纹章+【x】","水属性精灵：初始暴率+【x】\\n水属性精灵：初始暴伤+【x1】"],"ProOneID":[2009,3506,3506,8],"ValueOne":[10000,1000,1000,50],"TargetOne":[516,516,516,521],"AddOne":[10000,1000,1000,50],"MulOne":[10000,10000,10000,10000],"ProTwoID":9,"ValuTwo":50,"TargetTwo":521,"AddTwo":50,"MulTwo":10000,"FinalTitle":["百万进化","狂暴光环","种族跃迁"],"FinalDas":["暴鲤龙进化+6后解锁百万进化，百万进化效果：品质提升为红色，实力大幅提升，技能效果大幅提升！","水属性精灵：初始暴率+5%\\n水属性精灵：初始暴伤+25%\\n队伍精灵：强化等级上限+40","暴鲤龙所有进化形态，初始攻击+20，初始生命+200，初始防御+4\\n暴鲤龙+1，强化等级上限额外+10\\n暴鲤龙+2，强化等级上限额外+20\\n暴鲤龙+3，强化等级上限额外+30\\n暴鲤龙+4，强化等级上限额外+40\\n暴鲤龙+5，强化等级上限额外+50\\n暴鲤龙+6，强化等级上限额外+60\\n超级暴鲤龙，强化等级上限额外+70"],"RedID":[1,2,30,3210,8,9],"RedValue":[20,200,4,40,500,500],"RedTarget":[540,540,540,516,521,521],"LevelBonus":[10,20,30,40,50,60,70]},"105503":{"Name":"杰尼龟进化钥石","Icon":"HF-JieNiGui","Define":"解锁杰尼龟百万进化的神奇钥石，将钥石品质跃升到红色品质，杰尼龟进化+6后精灵进化接口即可解锁超酷的百万进化。","PieceID":754,"CardID":1055030,"Des":["精灵强化金币-【x】","水属性精灵：初始生命+【x】\\n水属性精灵：初始物防+【x1】","水属性精灵：初始生命+【x】\\n水属性精灵：初始法防+【x1】","水属性精灵：初始生命+【x】\\n水属性精灵：初始攻击+【x1】"],"ProOneID":[2007,52,52,52],"ValueOne":[12000,50,50,50],"TargetOne":[516,521,521,521],"AddOne":[50,50,50],"MulOne":[12078,10000,10000,10000],"ProTwoID":[53,54,51],"ValuTwo":[50,50,50],"TargetTwo":[521,521,521],"AddTwo":[50,50,50],"MulTwo":[10000,10000,10000],"FinalTitle":["百万进化","生命蜕变","种族跃迁"],"FinalDas":["杰尼龟进化+6后解锁百万进化，百万进化效果：品质提升为红色，实力大幅提升，技能效果大幅提升！","水属性精灵：初始生命+25%\\n队伍精灵：强化等级上限+40","杰尼龟所有进化形态，初始攻击+20，初始生命+200，初始防御+4\\n卡咪龟+1，强化等级上限额外+20\\n水箭龟+2，强化等级上限额外+40\\n水箭龟+3，强化等级上限额外+60\\n水箭龟+4，强化等级上限额外+80\\n水箭龟+5，强化等级上限额外+100\\n水箭龟+6，强化等级上限额外+120\\n超级水箭龟，强化等级上限额外+140"],"RedID":[1,2,30,3210,52,0],"RedValue":[20,200,4,40,2500,0],"RedTarget":[540,540,540,516,521,0],"LevelBonus":[15,30,45,60,75,90,105]},"106301":{"Name":"卡拉卡拉进化钥石","Icon":"HF-KaLaKaLa","Define":"解锁卡拉卡拉百万进化的神奇钥石，将钥石品质跃升到红色品质，卡拉卡拉进化+6后精灵进化接口即可解锁超酷的百万进化。","PieceID":718,"CardID":1063010,"Des":["工作最终金币+【x】","地面属性精灵：初始生命+【x】\\n地面属性精灵：初始物防+【x1】","地面属性精灵：初始生命+【x】\\n地面属性精灵：初始法防+【x1】","地面属性精灵：初始生命+【x】\\n地面属性精灵：初始攻击+【x1】"],"ProOneID":[2009,52,52,52],"ValueOne":[10000,50,50,50],"TargetOne":[516,522,522,522],"AddOne":[10000,50,50,50],"MulOne":[10000,10000,10000,10000],"ProTwoID":[53,54,51],"ValuTwo":[50,50,50],"TargetTwo":[522,522,522],"AddTwo":[50,50,50],"MulTwo":[10000,10000,10000],"FinalTitle":["百万进化","生命蜕变","种族跃迁"],"FinalDas":["卡拉卡拉进化+6后解锁百万进化，百万进化效果：品质提升为红色，实力大幅提升，技能效果大幅提升！","地面属性精灵：初始生命+25%\\n队伍精灵：强化等级上限+40","卡拉卡拉所有进化形态，初始攻击+20，初始生命+200，初始防御+4\\n嘎啦嘎啦+1，强化等级上限额外+10\\n嘎啦嘎啦+2，强化等级上限额外+20\\n嘎啦嘎啦+3，强化等级上限额外+30\\n嘎啦嘎啦+4，强化等级上限额外+40\\n嘎啦嘎啦+5，强化等级上限额外+50\\n嘎啦嘎啦+6，强化等级上限额外+60\\n超级嘎啦嘎啦，强化等级上限额外+70"],"RedID":[1,2,30,3210,52,0],"RedValue":[20,200,4,40,2500,0],"RedTarget":[540,540,540,516,522,0],"LevelBonus":[10,20,30,40,50,60,70]},"106502":{"Name":"螺钉地鼠进化钥石","Icon":"HF-LuoDingDiShu","Define":"解锁螺钉地鼠百万进化的神奇钥石，将钥石品质跃升到红色品质，螺钉地鼠进化+6后精灵进化接口即可解锁超酷的百万进化。","PieceID":743,"CardID":1065020,"Des":["工作最终金币+【x】","里程碑纹章+【x】","里程碑纹章+【x】","地面属性精灵：初始暴率+【x】\\n地面属性精灵：初始暴伤+【x1】"],"ProOneID":[2009,3506,3506,8],"ValueOne":[10000,1000,1000,50],"TargetOne":[516,516,516,522],"AddOne":[10000,1000,1000,50],"MulOne":[10000,10000,10000,10000],"ProTwoID":9,"ValuTwo":50,"TargetTwo":522,"AddTwo":50,"MulTwo":10000,"FinalTitle":["百万进化","狂暴光环","种族跃迁"],"FinalDas":["螺钉地鼠进化+6后解锁百万进化，百万进化效果：品质提升为红色，实力大幅提升，技能效果大幅提升！","地面属性精灵：初始暴率+5%\\n地面属性精灵：初始暴伤+25%\\n队伍精灵：强化等级上限+40","螺钉地鼠所有进化形态，初始攻击+20，初始生命+200，初始防御+4\\n螺钉地鼠+1，强化等级上限额外+20\\n螺钉地鼠+2，强化等级上限额外+40\\n螺钉地鼠+3，强化等级上限额外+60\\n螺钉地鼠+4，强化等级上限额外+80\\n螺钉地鼠+5，强化等级上限额外+100\\n螺钉地鼠+6，强化等级上限额外+120\\n超级螺钉地鼠，强化等级上限额外+140"],"RedID":[1,2,30,3210,8,9],"RedValue":[20,200,4,40,500,500],"RedTarget":[540,540,540,516,522,522],"LevelBonus":[15,30,45,60,75,90,105]},"107202":{"Name":"咩利羊进化钥石","Icon":"HF-MieLiYang","Define":"解锁咩利羊百万进化的神奇钥石，将钥石品质跃升到红色品质，咩利羊进化+6后精灵进化接口即可解锁超酷的百万进化。","PieceID":710,"CardID":1072020,"Des":["工作升级金币-【x】","电属性精灵：初始生命+【x】\\n电属性精灵：初始物防+【x1】","电属性精灵：初始生命+【x】\\n电属性精灵：初始法防+【x1】","电属性精灵：初始生命+【x】\\n电属性精灵：初始攻击+【x1】"],"ProOneID":[2006,52,52,52],"ValueOne":[12000,50,50,50],"TargetOne":[516,523,523,523],"AddOne":[50,50,50],"MulOne":[12078,10000,10000,10000],"ProTwoID":[53,54,51],"ValuTwo":[50,50,50],"TargetTwo":[523,523,523],"AddTwo":[50,50,50],"MulTwo":[10000,10000,10000],"FinalTitle":["百万进化","生命蜕变","种族跃迁"],"FinalDas":["咩利羊进化+6后解锁百万进化，百万进化效果：品质提升为红色，实力大幅提升，技能效果大幅提升！","电属性精灵：初始生命+25%\\n队伍精灵：强化等级上限+40","咩利羊所有进化形态，初始攻击+20，初始生命+200，初始防御+4\\n茸茸羊+1，强化等级上限额外+5\\n电龙+2，强化等级上限额外+10\\n电龙+3，强化等级上限额外+15\\n电龙+4，强化等级上限额外+20\\n电龙+5，强化等级上限额外+25\\n电龙+6，强化等级上限额外+30\\n超级电龙，强化等级上限额外+35"],"RedID":[1,2,30,3210,52,0],"RedValue":[20,200,4,40,2500,0],"RedTarget":[540,540,540,516,523,0],"LevelBonus":[5,10,15,20,25,30,35]},"107503":{"Name":"皮丘进化钥石","Icon":"HF-PiKaQiu","Define":"解锁皮丘百万进化的神奇钥石，将钥石品质跃升到红色品质，皮丘进化+6后精灵进化接口即可解锁超酷的百万进化。","PieceID":755,"CardID":1075030,"Des":["工作最终金币+【x】","里程碑纹章+【x】","里程碑纹章+【x】","电属性精灵：初始暴率+【x】\\n电属性精灵：初始暴伤+【x1】"],"ProOneID":[2009,3506,3506,8],"ValueOne":[15000,1000,1000,50],"TargetOne":[516,516,516,523],"AddOne":[10000,1000,1000,50],"MulOne":[10000,10000,10000,10000],"ProTwoID":9,"ValuTwo":50,"TargetTwo":523,"AddTwo":50,"MulTwo":10000,"FinalTitle":["百万进化","狂暴光环","种族跃迁"],"FinalDas":["皮丘进化+6后解锁百万进化，百万进化效果：品质提升为红色，实力大幅提升，技能效果大幅提升！","电属性精灵：初始暴率+5%\\n电属性精灵：初始暴伤+25%\\n队伍精灵：强化等级上限+40","皮丘所有进化形态，初始攻击+20，初始生命+200，初始防御+4\\n皮卡丘+1，强化等级上限额外+20\\n雷丘+2，强化等级上限额外+40\\n雷丘+3，强化等级上限额外+60\\n雷丘+4，强化等级上限额外+80\\n雷丘+5，强化等级上限额外+100\\n雷丘+6，强化等级上限额外+120\\n超级雷丘，强化等级上限额外+140"],"RedID":[1,2,30,3210,8,9],"RedValue":[20,200,4,40,500,500],"RedTarget":[540,540,540,516,523,523],"LevelBonus":[15,30,45,60,75,90,105]},"108502":{"Name":"超梦进化钥石","Icon":"HF-ChaoMeng","Define":"解锁超梦百万进化的神奇钥石，将钥石品质跃升到红色品质，超梦进化+6后精灵进化接口即可解锁超酷的百万进化。","PieceID":784,"CardID":1085020,"Des":["工作最终金币+【x】","精灵强化金币-【x】","工作升级金币-【x】","工作时间-【x】"],"ProOneID":[2009,2007,2006,2003],"ValueOne":[30000,15000,15000,15000],"TargetOne":[516,516,516,516],"AddOne":[10000,0,0,0],"MulOne":[10000,12195,12195,11845],"ProTwoID":0,"ValuTwo":0,"TargetTwo":0,"AddTwo":0,"MulTwo":0,"FinalTitle":["百万进化","大师纹章","种族跃迁"],"FinalDas":["超梦进化+6后解锁百万进化，百万进化效果：实力大幅提升，技能效果大幅提升！","关卡重置：里程碑纹章+1000%\\n队伍精灵：强化等级上限+40","超梦所有进化形态，初始攻击+20，初始生命+200，初始防御+4\\n超梦+1，强化等级上限额外+20\\n超梦+2，强化等级上限额外+40\\n超梦+3，强化等级上限额外+60\\n超梦+4，强化等级上限额外+80\\n超梦+5，强化等级上限额外+100\\n超梦+6，强化等级上限额外+120\\n超级超梦，强化等级上限额外+140"],"RedID":[1,2,30,3210,3506,0],"RedValue":[20,200,4,40,100000,0],"RedTarget":[540,540,540,516,516,0],"LevelBonus":[20,40,60,80,100,120,140]},"108506":{"Name":"卡西进化钥石","Icon":"HF-KaiXi","Define":"解锁卡西百万进化的神奇钥石，将钥石品质跃升到红色品质，卡西进化+6后精灵进化接口即可解锁超酷的百万进化。","PieceID":744,"CardID":1085060,"Des":["工作最终金币+【x】","超能力属性精灵：初始生命+【x】\\n超能力属性精灵：初始物防+【x1】","超能力属性精灵：初始生命+【x】\\n超能力属性精灵：初始法防+【x1】","超能力属性精灵：初始生命+【x】\\n超能力属性精灵：初始攻击+【x1】"],"ProOneID":[2009,52,52,52],"ValueOne":[15000,50,50,50],"TargetOne":[516,524,524,524],"AddOne":[10000,50,50,50],"MulOne":[10000,10000,10000,10000],"ProTwoID":[53,54,51],"ValuTwo":[50,50,50],"TargetTwo":[524,524,524],"AddTwo":[50,50,50],"MulTwo":[10000,10000,10000],"FinalTitle":["百万进化","生命蜕变","种族跃迁"],"FinalDas":["卡西进化+6后解锁百万进化，百万进化效果：品质提升为红色，实力大幅提升，技能效果大幅提升！","超能力属性精灵：初始生命+25%\\n队伍精灵：强化等级上限+40","卡西所有进化形态，初始攻击+20，初始生命+200，初始防御+4\\n勇基拉+1，强化等级上限额外+20\\n胡地+2，强化等级上限额外+40\\n胡地+3，强化等级上限额外+60\\n胡地+4，强化等级上限额外+80\\n胡地+5，强化等级上限额外+100\\n胡地+6，强化等级上限额外+120\\n超级胡地，强化等级上限额外+140"],"RedID":[1,2,30,3210,52,0],"RedValue":[20,200,4,40,2500,0],"RedTarget":[540,540,540,516,524,0],"LevelBonus":[15,30,45,60,75,90,105]},"108507":{"Name":"拉鲁拉丝进化钥石","Icon":"HF-LaLuLaSi","Define":"解锁拉鲁拉丝百万进化的神奇钥石，将钥石品质跃升到红色品质，拉鲁拉丝进化+6后精灵进化接口即可解锁超酷的百万进化。","PieceID":745,"CardID":1085070,"Des":["工作最终金币+【x】","里程碑纹章+【x】","里程碑纹章+【x】","超能力属性精灵：初始暴率+【x】\\n超能力属性精灵：初始暴伤+【x1】"],"ProOneID":[2009,3506,3506,8],"ValueOne":[10000,1000,1000,50],"TargetOne":[516,516,516,524],"AddOne":[10000,1000,1000,50],"MulOne":[10000,10000,10000,10000],"ProTwoID":9,"ValuTwo":50,"TargetTwo":524,"AddTwo":50,"MulTwo":10000,"FinalTitle":["百万进化","狂暴光环","种族跃迁"],"FinalDas":["拉鲁拉丝进化+6后解锁百万进化，百万进化效果：品质提升为红色，实力大幅提升，技能效果大幅提升！","超能力属性精灵：初始暴率+5%\\n超能力属性精灵：初始暴伤+25%\\n队伍精灵：强化等级上限+40","拉鲁拉丝所有进化形态，初始攻击+20，初始生命+200，初始防御+4\\n奇鲁莉安+1，强化等级上限额外+20\\n沙奈朵+2，强化等级上限额外+40\\n沙奈朵+3，强化等级上限额外+60\\n沙奈朵+4，强化等级上限额外+80\\n沙奈朵+5，强化等级上限额外+100\\n沙奈朵+6，强化等级上限额外+120\\n超级沙奈朵，强化等级上限额外+140"],"RedID":[1,2,30,3210,8,9],"RedValue":[20,200,4,40,500,500],"RedTarget":[540,540,540,516,524,524],"LevelBonus":[15,30,45,60,75,90,105]},"109401":{"Name":"瓦斯弹进化钥石","Icon":"HF-WaSiDan","Define":"解锁瓦斯弹百万进化的神奇钥石，将钥石品质跃升到红色品质，瓦斯弹进化+6后精灵进化接口即可解锁超酷的百万进化。","PieceID":731,"CardID":1094010,"Des":["工作最终金币+【x】","里程碑纹章+【x】","里程碑纹章+【x】","毒属性精灵：初始暴率+【x】\\n毒属性精灵：初始暴伤+【x1】"],"ProOneID":[2009,3506,3506,8],"ValueOne":[10000,1000,1000,50],"TargetOne":[516,516,516,525],"AddOne":[10000,1000,1000,50],"MulOne":[10000,10000,10000,10000],"ProTwoID":9,"ValuTwo":50,"TargetTwo":525,"AddTwo":50,"MulTwo":10000,"FinalTitle":["百万进化","狂暴光环","种族跃迁"],"FinalDas":["瓦斯弹进化+6后解锁百万进化，百万进化效果：品质提升为红色，实力大幅提升，技能效果大幅提升！","毒属性精灵：初始暴率+5%\\n毒属性精灵：初始暴伤+25%\\n队伍精灵：强化等级上限+40","瓦斯弹所有进化形态，初始攻击+20，初始生命+200，初始防御+4\\n瓦斯弹+1，强化等级上限额外+10\\n瓦斯弹+2，强化等级上限额外+20\\n瓦斯弹+3，强化等级上限额外+30\\n瓦斯弹+4，强化等级上限额外+40\\n瓦斯弹+5，强化等级上限额外+50\\n瓦斯弹+6，强化等级上限额外+60\\n超级瓦斯弹，强化等级上限额外+70"],"RedID":[1,2,30,3210,8,9],"RedValue":[20,200,4,40,500,500],"RedTarget":[540,540,540,516,525,525],"LevelBonus":[10,20,30,40,50,60,70]},"109508":{"Name":"溶食兽进化钥石","Icon":"HF-RongShiShou","Define":"解锁溶食兽百万进化的神奇钥石，将钥石品质跃升到红色品质，溶食兽进化+6后精灵进化接口即可解锁超酷的百万进化。","PieceID":756,"CardID":1095080,"Des":["工作最终金币+【x】","毒属性精灵：初始生命+【x】\\n毒属性精灵：初始物防+【x1】","毒属性精灵：初始生命+【x】\\n毒属性精灵：初始法防+【x1】","毒属性精灵：初始生命+【x】\\n毒属性精灵：初始攻击+【x1】"],"ProOneID":[2009,52,52,52],"ValueOne":[15000,50,50,50],"TargetOne":[516,525,525,525],"AddOne":[10000,50,50,50],"MulOne":[10000,10000,10000,10000],"ProTwoID":[53,54,51],"ValuTwo":[50,50,50],"TargetTwo":[525,525,525],"AddTwo":[50,50,50],"MulTwo":[10000,10000,10000],"FinalTitle":["百万进化","生命蜕变","种族跃迁"],"FinalDas":["溶食兽进化+6后解锁百万进化，百万进化效果：品质提升为红色，实力大幅提升，技能效果大幅提升！","毒属性精灵：初始生命+25%\\n队伍精灵：强化等级上限+40","溶食兽所有进化形态，初始攻击+20，初始生命+200，初始防御+4\\n溶食兽+1，强化等级上限额外+20\\n溶食兽+2，强化等级上限额外+40\\n溶食兽+3，强化等级上限额外+60\\n溶食兽+4，强化等级上限额外+80\\n溶食兽+5，强化等级上限额外+100\\n溶食兽+6，强化等级上限额外+120\\n超级溶食兽，强化等级上限额外+140"],"RedID":[1,2,30,3210,52,0],"RedValue":[20,200,4,40,2500,0],"RedTarget":[540,540,540,516,525,0],"LevelBonus":[15,30,45,60,75,90,105]},"110401":{"Name":"皮皮进化钥石","Icon":"HF-PiPi","Define":"解锁皮皮百万进化的神奇钥石，将钥石品质跃升到红色品质，皮皮进化+6后精灵进化接口即可解锁超酷的百万进化。","PieceID":732,"CardID":1104010,"Des":["工作最终金币+【x】","里程碑纹章+【x】","里程碑纹章+【x】","妖精属性精灵：初始暴率+【x】\\n妖精属性精灵：初始暴伤+【x1】"],"ProOneID":[2009,3506,3506,8],"ValueOne":[10000,1000,1000,50],"TargetOne":[516,516,516,526],"AddOne":[10000,1000,1000,50],"MulOne":[10000,10000,10000,10000],"ProTwoID":9,"ValuTwo":50,"TargetTwo":526,"AddTwo":50,"MulTwo":10000,"FinalTitle":["百万进化","狂暴光环","种族跃迁"],"FinalDas":["皮皮进化+6后解锁百万进化，百万进化效果：品质提升为红色，实力大幅提升，技能效果大幅提升！","妖精属性精灵：初始暴率+5%\\n妖精属性精灵：初始暴伤+25%\\n队伍精灵：强化等级上限+40","皮皮所有进化形态，初始攻击+20，初始生命+200，初始防御+4\\n皮皮+1，强化等级上限额外+10\\n皮皮+2，强化等级上限额外+20\\n皮皮+3，强化等级上限额外+30\\n皮皮+4，强化等级上限额外+40\\n皮皮+5，强化等级上限额外+50\\n皮皮+6，强化等级上限额外+60\\n超级皮皮，强化等级上限额外+70"],"RedID":[1,2,30,3210,8,9],"RedValue":[20,200,4,40,500,500],"RedTarget":[540,540,540,516,526,526],"LevelBonus":[10,20,30,40,50,60,70]},"110502":{"Name":"波克比进化钥石","Icon":"HF-BoKeBi","Define":"解锁波克比百万进化的神奇钥石，将钥石品质跃升到红色品质，波克比进化+6后精灵进化接口即可解锁超酷的百万进化。","PieceID":757,"CardID":1105020,"Des":["工作最终金币+【x】","妖精属性精灵：初始生命+【x】\\n妖精属性精灵：初始物防+【x1】","妖精属性精灵：初始生命+【x】\\n妖精属性精灵：初始法防+【x1】","妖精属性精灵：初始生命+【x】\\n妖精属性精灵：初始攻击+【x1】"],"ProOneID":[2009,52,52,52],"ValueOne":[15000,50,50,50],"TargetOne":[516,526,526,526],"AddOne":[10000,50,50,50],"MulOne":[10000,10000,10000,10000],"ProTwoID":[53,54,51],"ValuTwo":[50,50,50],"TargetTwo":[526,526,526],"AddTwo":[50,50,50],"MulTwo":[10000,10000,10000],"FinalTitle":["百万进化","生命蜕变","种族跃迁"],"FinalDas":["波克比进化+6后解锁百万进化，百万进化效果：品质提升为红色，实力大幅提升，技能效果大幅提升！","妖精属性精灵：初始生命+25%\\n队伍精灵：强化等级上限+40","波克比所有进化形态，初始攻击+20，初始生命+200，初始防御+4\\n波克比+1，强化等级上限额外+20\\n波克比+2，强化等级上限额外+40\\n波克比+3，强化等级上限额外+60\\n波克比+4，强化等级上限额外+80\\n波克比+5，强化等级上限额外+100\\n波克比+6，强化等级上限额外+120\\n超级波克比，强化等级上限额外+140"],"RedID":[1,2,30,3210,52,0],"RedValue":[20,200,4,40,2500,0],"RedTarget":[540,540,540,516,526,0],"LevelBonus":[15,30,45,60,75,90,105]},"111501":{"Name":"路卡利欧进化钥石","Icon":"HF-LuKaLiOu","Define":"解锁路卡利欧百万进化的神奇钥石，将钥石品质跃升到红色品质，路卡利欧进化+6后精灵进化接口即可解锁超酷的百万进化。","PieceID":758,"CardID":1115010,"Des":["工作最终金币+【x】","格斗属性精灵：初始生命+【x】\\n格斗属性精灵：初始物防+【x1】","格斗属性精灵：初始生命+【x】\\n格斗属性精灵：初始法防+【x1】","格斗属性精灵：初始生命+【x】\\n格斗属性精灵：初始攻击+【x1】"],"ProOneID":[2009,52,52,52],"ValueOne":[10000,50,50,50],"TargetOne":[516,527,527,527],"AddOne":[10000,50,50,50],"MulOne":[10000,10000,10000,10000],"ProTwoID":[53,54,51],"ValuTwo":[50,50,50],"TargetTwo":[527,527,527],"AddTwo":[50,50,50],"MulTwo":[10000,10000,10000],"FinalTitle":["百万进化","生命蜕变","种族跃迁"],"FinalDas":["路卡利欧进化+6后解锁百万进化，百万进化效果：品质提升为红色，实力大幅提升，技能效果大幅提升！","格斗属性精灵：初始生命+25%\\n队伍精灵：强化等级上限+40","路卡利欧所有进化形态，初始攻击+20，初始生命+200，初始防御+4\\n路卡利欧+1，强化等级上限额外+20\\n路卡利欧+2，强化等级上限额外+40\\n路卡利欧+3，强化等级上限额外+60\\n路卡利欧+4，强化等级上限额外+80\\n路卡利欧+5，强化等级上限额外+100\\n路卡利欧+6，强化等级上限额外+120\\n超级路卡利欧，强化等级上限额外+140"],"RedID":[1,2,30,3210,52,0],"RedValue":[20,200,4,40,2500,0],"RedTarget":[540,540,540,516,527,0],"LevelBonus":[15,30,45,60,75,90,105]},"111502":{"Name":"腕力进化钥石","Icon":"HF-WanLi","Define":"解锁腕力百万进化的神奇钥石，将钥石品质跃升到红色品质，腕力进化+6后精灵进化接口即可解锁超酷的百万进化。","PieceID":747,"CardID":1115020,"Des":["工作最终金币+【x】","里程碑纹章+【x】","里程碑纹章+【x】","格斗属性精灵：初始暴率+【x】\\n格斗属性精灵：初始暴伤+【x1】"],"ProOneID":[2009,3506,3506,8],"ValueOne":[15000,1000,1000,50],"TargetOne":[516,516,516,527],"AddOne":[10000,1000,1000,50],"MulOne":[10000,10000,10000,10000],"ProTwoID":9,"ValuTwo":50,"TargetTwo":527,"AddTwo":50,"MulTwo":10000,"FinalTitle":["百万进化","狂暴光环","种族跃迁"],"FinalDas":["腕力进化+6后解锁百万进化，百万进化效果：品质提升为红色，实力大幅提升，技能效果大幅提升！","格斗属性精灵：初始暴率+5%\\n格斗属性精灵：初始暴伤+25%\\n队伍精灵：强化等级上限+40","腕力所有进化形态，初始攻击+20，初始生命+200，初始防御+4\\n豪力+1，强化等级上限额外+20\\n怪力+2，强化等级上限额外+40\\n怪力+3，强化等级上限额外+60\\n怪力+4，强化等级上限额外+80\\n怪力+5，强化等级上限额外+100\\n怪力+6，强化等级上限额外+120\\n超级怪力，强化等级上限额外+140"],"RedID":[1,2,30,3210,8,9],"RedValue":[20,200,4,40,500,500],"RedTarget":[540,540,540,516,527,527],"LevelBonus":[15,30,45,60,75,90,105]},"112101":{"Name":"可可多拉进化钥石","Icon":"HF-KeKeDuoLa","Define":"解锁可可多拉百万进化的神奇钥石，将钥石品质跃升到红色品质，可可多拉进化+6后精灵进化接口即可解锁超酷的百万进化。","PieceID":704,"CardID":1121010,"Des":["工作最终金币+【x】","钢属性精灵：初始生命+【x】\\n钢属性精灵：初始物防+【x1】","钢属性精灵：初始生命+【x】\\n钢属性精灵：初始法防+【x1】","钢属性精灵：初始生命+【x】\\n钢属性精灵：初始攻击+【x1】"],"ProOneID":[2009,52,52,52],"ValueOne":[15000,50,50,50],"TargetOne":[516,528,528,528],"AddOne":[10000,50,50,50],"MulOne":[10000,10000,10000,10000],"ProTwoID":[53,54,51],"ValuTwo":[50,50,50],"TargetTwo":[528,528,528],"AddTwo":[50,50,50],"MulTwo":[10000,10000,10000],"FinalTitle":["百万进化","生命蜕变","种族跃迁"],"FinalDas":["可可多拉进化+6后解锁百万进化，百万进化效果：品质提升为红色，实力大幅提升，技能效果大幅提升！","钢属性精灵：初始生命+25%\\n队伍精灵：强化等级上限+40","可可多拉所有进化形态，初始攻击+20，初始生命+200，初始防御+4\\n可多拉+1，强化等级上限额外+5\\n可多拉+2，强化等级上限额外+10\\n可多拉+3，强化等级上限额外+15\\n可多拉+4，强化等级上限额外+20\\n可多拉+5，强化等级上限额外+25\\n可多拉+6，强化等级上限额外+30\\n超级可多拉，强化等级上限额外+35"],"RedID":[1,2,30,3210,52,0],"RedValue":[20,200,4,40,2500,0],"RedTarget":[540,540,540,516,528,0],"LevelBonus":[5,10,15,20,25,30,35]},"112401":{"Name":"铁哑铃进化钥石","Icon":"HF-TieYaLing","Define":"解锁铁哑铃百万进化的神奇钥石，将钥石品质跃升到红色品质，铁哑铃进化+6后精灵进化接口即可解锁超酷的百万进化。","PieceID":733,"CardID":1124010,"Des":["工作最终金币+【x】","里程碑纹章+【x】","里程碑纹章+【x】","钢属性精灵：初始暴率+【x】\\n钢属性精灵：初始暴伤+【x1】"],"ProOneID":[2009,3506,3506,8],"ValueOne":[10000,1000,1000,50],"TargetOne":[516,516,516,528],"AddOne":[10000,1000,1000,50],"MulOne":[10000,10000,10000,10000],"ProTwoID":9,"ValuTwo":50,"TargetTwo":528,"AddTwo":50,"MulTwo":10000,"FinalTitle":["百万进化","狂暴光环","种族跃迁"],"FinalDas":["铁哑铃进化+6后解锁百万进化，百万进化效果：品质提升为红色，实力大幅提升，技能效果大幅提升！","钢属性精灵：初始暴率+5%\\n钢属性精灵：初始暴伤+25%\\n队伍精灵：强化等级上限+40","铁哑铃所有进化形态，初始攻击+20，初始生命+200，初始防御+4\\n铁哑铃+1，强化等级上限额外+10\\n铁哑铃+2，强化等级上限额外+20\\n铁哑铃+3，强化等级上限额外+30\\n铁哑铃+4，强化等级上限额外+40\\n铁哑铃+5，强化等级上限额外+50\\n铁哑铃+6，强化等级上限额外+60\\n超级铁哑铃，强化等级上限额外+70"],"RedID":[1,2,30,3210,8,9],"RedValue":[20,200,4,40,500,500],"RedTarget":[540,540,540,516,528,528],"LevelBonus":[10,20,30,40,50,60,70]},"113501":{"Name":"班吉拉斯进化钥石","Icon":"HF-BanJiLaSi","Define":"解锁班吉拉斯百万进化的神奇钥石，将钥石品质跃升到红色品质，班吉拉斯进化+6后精灵进化接口即可解锁超酷的百万进化。","PieceID":759,"CardID":1135010,"Des":["工作最终金币+【x】","岩石属性精灵：初始生命+【x】\\n岩石属性精灵：初始物防+【x1】","岩石属性精灵：初始生命+【x】\\n岩石属性精灵：初始法防+【x1】","岩石属性精灵：初始生命+【x】\\n岩石属性精灵：初始攻击+【x1】"],"ProOneID":[2009,52,52,52],"ValueOne":[15000,50,50,50],"TargetOne":[516,529,529,529],"AddOne":[10000,50,50,50],"MulOne":[10000,10000,10000,10000],"ProTwoID":[53,54,51],"ValuTwo":[50,50,50],"TargetTwo":[529,529,529],"AddTwo":[50,50,50],"MulTwo":[10000,10000,10000],"FinalTitle":["百万进化","生命蜕变","种族跃迁"],"FinalDas":["班吉拉斯进化+6后解锁百万进化，百万进化效果：品质提升为红色，实力大幅提升，技能效果大幅提升！","岩石属性精灵：初始生命+25%\\n队伍精灵：强化等级上限+40","班吉拉斯所有进化形态，初始攻击+20，初始生命+200，初始防御+4\\n班吉拉斯+1，强化等级上限额外+20\\n班吉拉斯+2，强化等级上限额外+40\\n班吉拉斯+3，强化等级上限额外+60\\n班吉拉斯+4，强化等级上限额外+80\\n班吉拉斯+5，强化等级上限额外+100\\n班吉拉斯+6，强化等级上限额外+120\\n超级班吉拉斯，强化等级上限额外+140"],"RedID":[1,2,30,3210,52,0],"RedValue":[20,200,4,40,2500,0],"RedTarget":[540,540,540,516,529,0],"LevelBonus":[15,30,45,60,75,90,105]},"113502":{"Name":"蒂安希进化钥石","Icon":"HF-DiAnXi","Define":"解锁蒂安希百万进化的神奇钥石，将钥石品质跃升到红色品质，蒂安希进化+6后精灵进化接口即可解锁超酷的百万进化。","PieceID":779,"CardID":1135020,"Des":["工作最终金币+【x】","精灵强化金币-【x】","工作升级金币-【x】","岩石属性精灵：初始暴率+【x】\\n岩石属性精灵：初始暴伤+【x1】"],"ProOneID":[2009,2007,2006,8],"ValueOne":[30000,12000,12000,50],"TargetOne":[516,516,516,529],"AddOne":[10000,0,0,50],"MulOne":[10000,12078,12078,10000],"ProTwoID":9,"ValuTwo":50,"TargetTwo":529,"AddTwo":50,"MulTwo":10000,"FinalTitle":["百万进化","狂暴光环","种族跃迁"],"FinalDas":["蒂安希进化+6后解锁百万进化，百万进化效果：实力大幅提升，技能效果大幅提升！","岩石属性精灵：初始暴率+5%\\n岩石属性精灵：初始暴伤+25%\\n队伍精灵：强化等级上限+40","蒂安希所有进化形态，初始攻击+20，初始生命+200，初始防御+4\\n蒂安希+1，强化等级上限额外+20\\n蒂安希+2，强化等级上限额外+40\\n蒂安希+3，强化等级上限额外+60\\n蒂安希+4，强化等级上限额外+80\\n蒂安希+5，强化等级上限额外+100\\n蒂安希+6，强化等级上限额外+120\\n超级蒂安希，强化等级上限额外+140"],"RedID":[1,2,30,3210,8,9],"RedValue":[20,200,4,40,500,500],"RedTarget":[540,540,540,516,529,529],"LevelBonus":[20,40,60,80,100,120,140]},"114201":{"Name":"独角虫进化钥石","Icon":"HF-DuJiaoChong","Define":"解锁独角虫百万进化的神奇钥石，将钥石品质跃升到红色品质，独角虫进化+6后精灵进化接口即可解锁超酷的百万进化。","PieceID":712,"CardID":1142010,"Des":["工作最终金币+【x】","里程碑纹章+【x】","里程碑纹章+【x】","虫属性精灵：初始暴率+【x】\\n虫属性精灵：初始暴伤+【x1】"],"ProOneID":[2009,3506,3506,8],"ValueOne":[10000,1000,1000,50],"TargetOne":[516,516,516,530],"AddOne":[10000,1000,1000,50],"MulOne":[10000,10000,10000,10000],"ProTwoID":9,"ValuTwo":50,"TargetTwo":530,"AddTwo":50,"MulTwo":10000,"FinalTitle":["百万进化","狂暴光环","种族跃迁"],"FinalDas":["独角虫进化+6后解锁百万进化，百万进化效果：品质提升为红色，实力大幅提升，技能效果大幅提升！","虫属性精灵：初始暴率+5%\\n虫属性精灵：初始暴伤+25%\\n队伍精灵：强化等级上限+40","独角虫所有进化形态，初始攻击+20，初始生命+200，初始防御+4\\n独角虫+1，强化等级上限额外+5\\n独角虫+2，强化等级上限额外+10\\n独角虫+3，强化等级上限额外+15\\n独角虫+4，强化等级上限额外+20\\n独角虫+5，强化等级上限额外+25\\n独角虫+6，强化等级上限额外+30\\n超级独角虫，强化等级上限额外+35"],"RedID":[1,2,30,3210,8,9],"RedValue":[20,200,4,40,500,500],"RedTarget":[540,540,540,516,530,530],"LevelBonus":[5,10,15,20,25,30,35]},"114504":{"Name":"巨钳螳螂进化钥石","Icon":"HF-JuQianTangLang","Define":"解锁巨钳螳螂百万进化的神奇钥石，将钥石品质跃升到红色品质，巨钳螳螂进化+6后精灵进化接口即可解锁超酷的百万进化。","PieceID":749,"CardID":1145040,"Des":["工作最终金币+【x】","虫属性精灵：初始生命+【x】\\n虫属性精灵：初始物防+【x1】","虫属性精灵：初始生命+【x】\\n虫属性精灵：初始法防+【x1】","虫属性精灵：初始生命+【x】\\n虫属性精灵：初始攻击+【x1】"],"ProOneID":[2009,52,52,52],"ValueOne":[10000,50,50,50],"TargetOne":[516,530,530,530],"AddOne":[10000,50,50,50],"MulOne":[10000,10000,10000,10000],"ProTwoID":[53,54,51],"ValuTwo":[50,50,50],"TargetTwo":[530,530,530],"AddTwo":[50,50,50],"MulTwo":[10000,10000,10000],"FinalTitle":["百万进化","生命蜕变","种族跃迁"],"FinalDas":["巨钳螳螂进化+6后解锁百万进化，百万进化效果：品质提升为红色，实力大幅提升，技能效果大幅提升！","虫属性精灵：初始生命+25%\\n队伍精灵：强化等级上限+40","巨钳螳螂所有进化形态，初始攻击+20，初始生命+200，初始防御+4\\n巨钳螳螂+1，强化等级上限额外+20\\n巨钳螳螂+2，强化等级上限额外+40\\n巨钳螳螂+3，强化等级上限额外+60\\n巨钳螳螂+4，强化等级上限额外+80\\n巨钳螳螂+5，强化等级上限额外+100\\n巨钳螳螂+6，强化等级上限额外+120\\n超级巨钳螳螂，强化等级上限额外+140"],"RedID":[1,2,30,3210,52,0],"RedValue":[20,200,4,40,2500,0],"RedTarget":[540,540,540,516,530,0],"LevelBonus":[15,30,45,60,75,90,105]},"115401":{"Name":"阿勃梭鲁进化钥石","Icon":"HF-ABoSuoLu","Define":"解锁阿勃梭鲁百万进化的神奇钥石，将钥石品质跃升到红色品质，阿勃梭鲁进化+6后精灵进化接口即可解锁超酷的百万进化。","PieceID":734,"CardID":1154010,"Des":["工作最终金币+【x】","恶属性精灵：初始生命+【x】\\n恶属性精灵：初始物防+【x1】","恶属性精灵：初始生命+【x】\\n恶属性精灵：初始法防+【x1】","恶属性精灵：初始生命+【x】\\n恶属性精灵：初始攻击+【x1】"],"ProOneID":[2009,52,52,52],"ValueOne":[10000,50,50,50],"TargetOne":[516,531,531,531],"AddOne":[10000,50,50,50],"MulOne":[10000,10000,10000,10000],"ProTwoID":[53,54,51],"ValuTwo":[50,50,50],"TargetTwo":[531,531,531],"AddTwo":[50,50,50],"MulTwo":[10000,10000,10000],"FinalTitle":["百万进化","生命蜕变","种族跃迁"],"FinalDas":["阿勃梭鲁进化+6后解锁百万进化，百万进化效果：品质提升为红色，实力大幅提升，技能效果大幅提升！","恶属性精灵：初始生命+25%\\n队伍精灵：强化等级上限+40","阿勃梭鲁所有进化形态，初始攻击+20，初始生命+200，初始防御+4\\n阿勃梭鲁+1，强化等级上限额外+10\\n阿勃梭鲁+2，强化等级上限额外+20\\n阿勃梭鲁+3，强化等级上限额外+30\\n阿勃梭鲁+4，强化等级上限额外+40\\n阿勃梭鲁+5，强化等级上限额外+50\\n阿勃梭鲁+6，强化等级上限额外+60\\n超级阿勃梭鲁，强化等级上限额外+70"],"RedID":[1,2,30,3210,52,0],"RedValue":[20,200,4,40,2500,0],"RedTarget":[540,540,540,516,531,0],"LevelBonus":[10,20,30,40,50,60,70]},"115502":{"Name":"达克莱伊进化钥石","Icon":"HF-DaKeLaiYi","Define":"解锁达克莱伊百万进化的神奇钥石，将钥石品质跃升到红色品质，达克莱伊进化+6后精灵进化接口即可解锁超酷的百万进化。","PieceID":781,"CardID":1155020,"Des":["工作最终金币+【x】","精灵强化金币-【x】","工作升级金币-【x】","恶属性精灵：初始暴率+【x】\\n恶属性精灵：初始暴伤+【x1】"],"ProOneID":[2009,2007,2006,8],"ValueOne":[30000,12000,12000,50],"TargetOne":[516,516,516,531],"AddOne":[10000,0,0,50],"MulOne":[10000,12078,12078,10000],"ProTwoID":9,"ValuTwo":50,"TargetTwo":531,"AddTwo":50,"MulTwo":10000,"FinalTitle":["百万进化","狂暴光环","种族跃迁"],"FinalDas":["达克莱伊进化+6后解锁百万进化，百万进化效果：实力大幅提升，技能效果大幅提升！","恶属性精灵：初始暴率+5%\\n恶属性精灵：初始暴伤+25%\\n队伍精灵：强化等级上限+40","达克莱伊所有进化形态，初始攻击+20，初始生命+200，初始防御+4\\n达克莱伊+1，强化等级上限额外+20\\n达克莱伊+2，强化等级上限额外+40\\n达克莱伊+3，强化等级上限额外+60\\n达克莱伊+4，强化等级上限额外+80\\n达克莱伊+5，强化等级上限额外+100\\n达克莱伊+6，强化等级上限额外+120\\n超级达克莱伊，强化等级上限额外+140"],"RedID":[1,2,30,3210,8,9],"RedValue":[20,200,4,40,500,500],"RedTarget":[540,540,540,516,531,531],"LevelBonus":[20,40,60,80,100,120,140]},"116201":{"Name":"诅咒娃娃进化钥石","Icon":"HF-ZuZhouWaWa","Define":"解锁诅咒娃娃百万进化的神奇钥石，将钥石品质跃升到红色品质，诅咒娃娃进化+6后精灵进化接口即可解锁超酷的百万进化。","PieceID":713,"CardID":1162010,"Des":["工作最终金币+【x】","幽灵属性精灵：初始生命+【x】\\n幽灵属性精灵：初始物防+【x1】","幽灵属性精灵：初始生命+【x】\\n幽灵属性精灵：初始法防+【x1】","幽灵属性精灵：初始生命+【x】\\n幽灵属性精灵：初始攻击+【x1】"],"ProOneID":[2009,52,52,52],"ValueOne":[10000,50,50,50],"TargetOne":[516,532,532,532],"AddOne":[10000,50,50,50],"MulOne":[10000,10000,10000,10000],"ProTwoID":[53,54,51],"ValuTwo":[50,50,50],"TargetTwo":[532,532,532],"AddTwo":[50,50,50],"MulTwo":[10000,10000,10000],"FinalTitle":["百万进化","生命蜕变","种族跃迁"],"FinalDas":["诅咒娃娃进化+6后解锁百万进化，百万进化效果：品质提升为红色，实力大幅提升，技能效果大幅提升！","幽灵属性精灵：初始生命+25%\\n队伍精灵：强化等级上限+40","诅咒娃娃所有进化形态，初始攻击+20，初始生命+200，初始防御+4\\n诅咒娃娃+1，强化等级上限额外+5\\n诅咒娃娃+2，强化等级上限额外+10\\n诅咒娃娃+3，强化等级上限额外+15\\n诅咒娃娃+4，强化等级上限额外+20\\n诅咒娃娃+5，强化等级上限额外+25\\n诅咒娃娃+6，强化等级上限额外+30\\n超级诅咒娃娃，强化等级上限额外+35"],"RedID":[1,2,30,3210,52,0],"RedValue":[20,200,4,40,2500,0],"RedTarget":[540,540,540,516,532,0],"LevelBonus":[5,10,15,20,25,30,35]},"116501":{"Name":"鬼斯进化钥石","Icon":"HF-GuiSi","Define":"解锁鬼斯百万进化的神奇钥石，将钥石品质跃升到红色品质，鬼斯进化+6后精灵进化接口即可解锁超酷的百万进化。","PieceID":750,"CardID":1165010,"Des":["工作最终金币+【x】","里程碑纹章+【x】","里程碑纹章+【x】","幽灵属性精灵：初始暴率+【x】\\n幽灵属性精灵：初始暴伤+【x1】"],"ProOneID":[2009,3506,3506,8],"ValueOne":[10000,1000,1000,50],"TargetOne":[516,516,516,532],"AddOne":[10000,1000,1000,50],"MulOne":[10000,10000,10000,10000],"ProTwoID":9,"ValuTwo":50,"TargetTwo":532,"AddTwo":50,"MulTwo":10000,"FinalTitle":["百万进化","狂暴光环","种族跃迁"],"FinalDas":["鬼斯进化+6后解锁百万进化，百万进化效果：品质提升为红色，实力大幅提升，技能效果大幅提升！","幽灵属性精灵：初始暴率+5%\\n幽灵属性精灵：初始暴伤+25%\\n队伍精灵：强化等级上限+40","鬼斯所有进化形态，初始攻击+20，初始生命+200，初始防御+4\\n鬼斯通+1，强化等级上限额外+20\\n耿鬼+2，强化等级上限额外+40\\n耿鬼+3，强化等级上限额外+60\\n耿鬼+4，强化等级上限额外+80\\n耿鬼+5，强化等级上限额外+100\\n耿鬼+6，强化等级上限额外+120\\n超级耿鬼，强化等级上限额外+140"],"RedID":[1,2,30,3210,8,9],"RedValue":[20,200,4,40,500,500],"RedTarget":[540,540,540,516,532,532],"LevelBonus":[15,30,45,60,75,90,105]},"117503":{"Name":"小卡比兽进化钥石","Icon":"HF-XiaoKaBiShou","Define":"解锁小卡比兽百万进化的神奇钥石，将钥石品质跃升到红色品质，小卡比兽进化+6后精灵进化接口即可解锁超酷的百万进化。","PieceID":751,"CardID":1175030,"Des":["工作最终金币+【x】","一般属性精灵：初始生命+【x】\\n一般属性精灵：初始物防+【x1】","一般属性精灵：初始生命+【x】\\n一般属性精灵：初始法防+【x1】","一般属性精灵：初始生命+【x】\\n一般属性精灵：初始攻击+【x1】"],"ProOneID":[2009,52,52,52],"ValueOne":[15000,50,50,50],"TargetOne":[516,533,533,533],"AddOne":[10000,50,50,50],"MulOne":[10000,10000,10000,10000],"ProTwoID":[53,54,51],"ValuTwo":[50,50,50],"TargetTwo":[533,533,533],"AddTwo":[50,50,50],"MulTwo":[10000,10000,10000],"FinalTitle":["百万进化","生命蜕变","种族跃迁"],"FinalDas":["小卡比兽进化+6后解锁百万进化，百万进化效果：品质提升为红色，实力大幅提升，技能效果大幅提升！","一般属性精灵：初始生命+25%\\n队伍精灵：强化等级上限+40","小卡比兽所有进化形态，初始攻击+20，初始生命+200，初始防御+4\\n小卡比兽+1，强化等级上限额外+20\\n小卡比兽+2，强化等级上限额外+40\\n小卡比兽+3，强化等级上限额外+60\\n小卡比兽+4，强化等级上限额外+80\\n小卡比兽+5，强化等级上限额外+100\\n小卡比兽+6，强化等级上限额外+120\\n超级小卡比兽，强化等级上限额外+140"],"RedID":[1,2,30,3210,52,0],"RedValue":[20,200,4,40,2500,0],"RedTarget":[540,540,540,516,533,0],"LevelBonus":[15,30,45,60,75,90,105]},"117504":{"Name":"喵喵进化钥石","Icon":"HF-MiaoMiao","Define":"解锁喵喵百万进化的神奇钥石，将钥石品质跃升到红色品质，喵喵进化+6后精灵进化接口即可解锁超酷的百万进化。","PieceID":761,"CardID":1175040,"Des":["工作最终金币+【x】","工作最终金币+【x】","工作最终金币+【x】","一般属性精灵：初始暴率+【x】\\n一般属性精灵：初始暴伤+【x1】"],"ProOneID":[2009,2009,2009,8],"ValueOne":[10000,10000,10000,50],"TargetOne":[516,516,516,533],"AddOne":[10000,10000,10000,50],"MulOne":[10000,10000,10000,10000],"ProTwoID":9,"ValuTwo":50,"TargetTwo":533,"AddTwo":50,"MulTwo":10000,"FinalTitle":["百万进化","狂暴光环","种族跃迁"],"FinalDas":["喵喵进化+6后解锁百万进化，百万进化效果：品质提升为红色，实力大幅提升，技能效果大幅提升！","一般属性精灵：初始暴率+5%\\n一般属性精灵：初始暴伤+25%\\n队伍精灵：强化等级上限+40","喵喵所有进化形态，初始攻击+20，初始生命+200，初始防御+4\\n喵喵+1，强化等级上限额外+20\\n喵喵+2，强化等级上限额外+40\\n喵喵+3，强化等级上限额外+60\\n喵喵+4，强化等级上限额外+80\\n喵喵+5，强化等级上限额外+100\\n喵喵+6，强化等级上限额外+120\\n超级喵喵，强化等级上限额外+140"],"RedID":[1,2,30,3210,8,9],"RedValue":[20,200,4,40,500,500],"RedTarget":[540,540,540,516,533,533],"LevelBonus":[15,30,45,60,75,90,105]}}}